canvas_workflow_helpers/__init__.py
canvas_workflow_helpers/protocols/__init__.py
canvas_workflow_helpers/protocols/appointment_notifications.py
canvas_workflow_helpers/protocols/appointment_task_creator.py
canvas_workflow_helpers/protocols/appointment_updater.py
canvas_workflow_helpers/protocols/banner_alerts_for_contacts.py
canvas_workflow_helpers/protocols/hyperlink_helpers.py
canvas_workflow_helpers/protocols/plan_command_recommendation.py
canvas_workflow_helpers/protocols/prescribe_command_recommendation.py
canvas_workflow_helpers/protocols/survey_driven_diagnosis.py
canvas_workflow_helpers/tests/__init__.py
canvas_workflow_helpers/tests/base.py
canvas_workflow_helpers/tests/mock_data/full_detailed_patient/allergy_intolerances.json
canvas_workflow_helpers/tests/mock_data/full_detailed_patient/billing_line_items.json
canvas_workflow_helpers/tests/mock_data/full_detailed_patient/conditions.json
canvas_workflow_helpers/tests/mock_data/full_detailed_patient/imaging_reports.json
canvas_workflow_helpers/tests/mock_data/full_detailed_patient/immunizations.json
canvas_workflow_helpers/tests/mock_data/full_detailed_patient/inpatient_stay.json
canvas_workflow_helpers/tests/mock_data/full_detailed_patient/instructions.json
canvas_workflow_helpers/tests/mock_data/full_detailed_patient/interviews.json
canvas_workflow_helpers/tests/mock_data/full_detailed_patient/lab_reports.json
canvas_workflow_helpers/tests/mock_data/full_detailed_patient/medications.json
canvas_workflow_helpers/tests/mock_data/full_detailed_patient/messages.json
canvas_workflow_helpers/tests/mock_data/full_detailed_patient/patient.json
canvas_workflow_helpers/tests/mock_data/full_detailed_patient/protocol_overrides.json
canvas_workflow_helpers/tests/mock_data/full_detailed_patient/protocols.json
canvas_workflow_helpers/tests/mock_data/full_detailed_patient/reason_for_visits.json
canvas_workflow_helpers/tests/mock_data/full_detailed_patient/referral_reports.json
canvas_workflow_helpers-0.1.0.dist-info/LICENSE
canvas_workflow_helpers-0.1.0.dist-info/WHEEL
canvas_workflow_helpers-0.1.0.dist-info/METADATA
canvas_workflow_helpers-0.1.0.dist-info/RECORD
