Metadata-Version: 2.1
Name: canvas-workflow-helpers
Version: 0.1.0
Summary: An open source project to empower customization of your Canvas instance using canvas-workflow-kit
License: Apache-2.0
Author: Canvas Team
Author-email: engineering@canvasmedical.com
Requires-Python: >=3.8,<4.0
Classifier: License :: OSI Approved :: Apache Software License
Classifier: Programming Language :: Python :: 3
Classifier: Programming Language :: Python :: 3.10
Classifier: Programming Language :: Python :: 3.8
Classifier: Programming Language :: Python :: 3.9
Requires-Dist: arrow (>=1.2.2,<2.0.0)
Requires-Dist: canvas-workflow-kit (>=0.4.5,<0.5.0)
